airbyte_api/__init__.py
airbyte_api/connections.py
airbyte_api/destinations.py
airbyte_api/health.py
airbyte_api/jobs.py
airbyte_api/organizations.py
airbyte_api/permissions.py
airbyte_api/sdk.py
airbyte_api/sdkconfiguration.py
airbyte_api/sources.py
airbyte_api/streams.py
airbyte_api/users.py
airbyte_api/workspaces.py
airbyte_api/_hooks/__init__.py
airbyte_api/_hooks/clientcredentials.py
airbyte_api/_hooks/registration.py
airbyte_api/_hooks/sdkhooks.py
airbyte_api/_hooks/types.py
airbyte_api/api/__init__.py
airbyte_api/api/canceljob.py
airbyte_api/api/createconnection.py
airbyte_api/api/createdestination.py
airbyte_api/api/createjob.py
airbyte_api/api/createorupdateworkspaceoauthcredentials.py
airbyte_api/api/createpermission.py
airbyte_api/api/createsource.py
airbyte_api/api/createworkspace.py
airbyte_api/api/deleteconnection.py
airbyte_api/api/deletedestination.py
airbyte_api/api/deletepermission.py
airbyte_api/api/deletesource.py
airbyte_api/api/deleteworkspace.py
airbyte_api/api/getconnection.py
airbyte_api/api/getdestination.py
airbyte_api/api/gethealthcheck.py
airbyte_api/api/getjob.py
airbyte_api/api/getpermission.py
airbyte_api/api/getsource.py
airbyte_api/api/getstreamproperties.py
airbyte_api/api/getworkspace.py
airbyte_api/api/initiateoauth.py
airbyte_api/api/listconnections.py
airbyte_api/api/listdestinations.py
airbyte_api/api/listjobs.py
airbyte_api/api/listorganizationsforuser.py
airbyte_api/api/listpermissions.py
airbyte_api/api/listsources.py
airbyte_api/api/listuserswithinanorganization.py
airbyte_api/api/listworkspaces.py
airbyte_api/api/patchconnection.py
airbyte_api/api/patchdestination.py
airbyte_api/api/patchsource.py
airbyte_api/api/putdestination.py
airbyte_api/api/putsource.py
airbyte_api/api/updatepermission.py
airbyte_api/api/updateworkspace.py
airbyte_api/errors/__init__.py
airbyte_api/errors/sdkerror.py
airbyte_api/models/__init__.py
airbyte_api/models/actortypeenum.py
airbyte_api/models/airbyteapiconnectionschedule.py
airbyte_api-0.52.1.dist-info/LICENSE.md
airbyte_api-0.52.1.dist-info/METADATA
airbyte_api-0.52.1.dist-info/WHEEL
airbyte_api-0.52.1.dist-info/top_level.txt
airbyte_api-0.52.1.dist-info/RECORD
